[{"__type__":"cc.SpriteFrame","content":{"name":"red_soldier_up3","texture":"bczFiRjv5DoIwdHz+TsHRR","rect":[29,92,174,243],"offset":[-53.5,-10],"originalSize":[339,407],"capInsets":[0,0,0,0]}},{"__type__":"cc.AnimationClip","_name":"red_soldier_up","_duration":0.6833333333333333,"speed":2,"curveData":{"comps":{"cc.Sprite":{"spriteFrame":[{"frame":0,"value":{"__uuid__":"52+DVxHxRBZad+aH2sLZHt"}},{"frame":0.16666666666666666,"value":{"__uuid__":"44RlsGQS5Eo6QiXyEkJ41x"}},{"frame":0.3333333333333333,"value":{"__uuid__":"213Y8aNoNG0bDzJ3PqKzw0"}},{"frame":0.5,"value":{"__uuid__":"e2wXSHHMlMOIkZ4Yl1VCt0"}},{"frame":0.6666666666666666,"value":{"__uuid__":"4cZlb8T+VGeaxjyWkkP6Kd"}}]}}}},{"__type__":"cc.SpriteFrame","content":{"name":"red_soldier_up2","texture":"65K5qJq7NMWb1gI0XN8ra3","rect":[29,92,174,243],"offset":[-53.5,-10],"originalSize":[339,407],"capInsets":[0,0,0,0]}},{"__type__":"cc.SpriteFrame","content":{"name":"red_soldier_up5","texture":"f5sn2HoDxLZbnzrK3P6/3N","rect":[29,92,174,243],"offset":[-53.5,-10],"originalSize":[339,407],"capInsets":[0,0,0,0]}},{"__type__":"cc.SpriteFrame","content":{"name":"red_soldier_up1","texture":"87Kd59Nr1NLILeCju6upku","rect":[56,93,147,242],"offset":[-40,-10.5],"originalSize":[339,407],"capInsets":[0,0,0,0]}},{"__type__":"cc.SpriteFrame","content":{"name":"red_soldier_up4","texture":"d2Sg74Y/pLkY5HiMlig3c9","rect":[29,37,174,298],"offset":[-53.5,17.5],"originalSize":[339,407],"capInsets":[0,0,0,0]}}]